odoo10_addon_sale_order_line_description-10.0.1.0.1-py3.8-nspkg.pth
odoo/addons/sale_order_line_description/README.rst
odoo/addons/sale_order_line_description/__init__.py
odoo/addons/sale_order_line_description/__manifest__.py
odoo/addons/sale_order_line_description/i18n/ca.po
odoo/addons/sale_order_line_description/i18n/de.po
odoo/addons/sale_order_line_description/i18n/es.po
odoo/addons/sale_order_line_description/i18n/es_VE.po
odoo/addons/sale_order_line_description/i18n/fr.po
odoo/addons/sale_order_line_description/i18n/hr.po
odoo/addons/sale_order_line_description/i18n/it.po
odoo/addons/sale_order_line_description/i18n/nl_NL.po
odoo/addons/sale_order_line_description/i18n/pt_BR.po
odoo/addons/sale_order_line_description/i18n/ro.po
odoo/addons/sale_order_line_description/i18n/sale_order_line_description.pot
odoo/addons/sale_order_line_description/i18n/sl.po
odoo/addons/sale_order_line_description/i18n/tr.po
odoo/addons/sale_order_line_description/i18n/tr_TR.po
odoo/addons/sale_order_line_description/models/__init__.py
odoo/addons/sale_order_line_description/models/res_config.py
odoo/addons/sale_order_line_description/models/sale.py
odoo/addons/sale_order_line_description/security/sale_security.xml
odoo/addons/sale_order_line_description/static/description/icon.png
odoo/addons/sale_order_line_description/tests/__init__.py
odoo/addons/sale_order_line_description/tests/test_sale.py
odoo/addons/sale_order_line_description/views/res_config_view.xml
odoo10_addon_sale_order_line_description-10.0.1.0.1.dist-info/METADATA
odoo10_addon_sale_order_line_description-10.0.1.0.1.dist-info/WHEEL
odoo10_addon_sale_order_line_description-10.0.1.0.1.dist-info/namespace_packages.txt
odoo10_addon_sale_order_line_description-10.0.1.0.1.dist-info/top_level.txt
odoo10_addon_sale_order_line_description-10.0.1.0.1.dist-info/RECORD
